LICENSE
MANIFEST.in
README.md
setup.cfg
setup.py
django_wbc.egg-info/PKG-INFO
django_wbc.egg-info/SOURCES.txt
django_wbc.egg-info/dependency_links.txt
django_wbc.egg-info/requires.txt
django_wbc.egg-info/top_level.txt
wbc/__init__.py
wbc/comments/__init__.py
wbc/comments/admin.py
wbc/comments/forms.py
wbc/comments/models.py
wbc/comments/tests.py
wbc/comments/migrations/0001_initial.py
wbc/comments/migrations/__init__.py
wbc/comments/templates/comments/comment.html
wbc/comments/templates/comments/form.html
wbc/comments/templates/comments/list.html
wbc/core/__init__.py
wbc/core/context_processors.py
wbc/core/forms.py
wbc/core/models.py
wbc/core/tests.py
wbc/core/views.py
wbc/core/management/__init__.py
wbc/core/management/commands/__init__.py
wbc/core/management/commands/load-fixtures.py
wbc/core/static/admin.css
wbc/core/static/adminmap.css
wbc/core/static/adminmap.js
wbc/core/static/list.html
wbc/core/static/list.js
wbc/core/static/map.css
wbc/core/static/map.js
wbc/core/static/page.css
wbc/core/static/placemap.js
wbc/core/static/style.css
wbc/core/static/font/DejaVuSansCondensed-Bold.ttf
wbc/core/static/font/DejaVuSansCondensed.ttf
wbc/core/static/font/DroidSans-Bold.ttf
wbc/core/static/font/DroidSans.ttf
wbc/core/static/font/DroidSansMono.ttf
wbc/core/static/font/TitilliumText25L.otf
wbc/core/static/font/TitilliumText25L001.otf
wbc/core/static/font/TitilliumText25L002.otf
wbc/core/static/font/TitilliumText25L003.otf
wbc/core/static/font/TitilliumText25L004.otf
wbc/core/static/font/TitilliumText25L005.otf
wbc/core/static/img/favicon.png
wbc/core/static/img/hintergrund.png
wbc/core/static/img/karte.png
wbc/core/static/img/rss-feed-icon.png
wbc/core/static/img/title.png
wbc/core/static/img/icons/dunkelblau.png
wbc/core/static/img/icons/dunkelblau_hover.png
wbc/core/static/img/icons/grau.png
wbc/core/static/img/icons/gruen.png
wbc/core/static/img/icons/orange_1.png
wbc/core/static/img/icons/orange_1_hover.png
wbc/core/static/img/icons/orange_2.png
wbc/core/static/img/icons/orange_2_hover.png
wbc/core/static/img/icons/orange_3.png
wbc/core/static/img/icons/orange_3_hover.png
wbc/core/static/img/icons/orange_4.png
