Metadata-Version: 1.1
Name: django-wbc
Version: 0.1.2
Summary: We-build.city is a Django module for a collaboration platform about participation in urban planning.
Home-page: https://github.com/webuildcity/wbc/
Author: Jochen Klar
Author-email: jochenklar@gmail.com
License: GNU Lesser General Public License v3 (LGPLv3)
Download-URL: https://github.com/webuildcity/wbc/archive/0.1.2.tar.gz
Platform: UNKNOWN
Classifier: Development Status :: 4 - Beta
Classifier: Environment :: Web Environment
Classifier: Intended Audience :: Other Audience
Classifier: License :: OSI Approved :: GNU Lesser General Public License v3 (LGPLv3)
Classifier: Operating System :: OS Independent
Classifier: Programming Language :: Python :: 2.7
Classifier: Framework :: Django :: 1.8
Classifier: Natural Language :: German
